llm_wrangler/__init__.py
llm_wrangler/__main__.py
llm_wrangler/core.py
llm_wrangler/main.py
llm_wrangler/py.typed
llm_wrangler-0.4.0.dist-info/entry_points.txt
llm_wrangler-0.4.0.dist-info/LICENSE
llm_wrangler-0.4.0.dist-info/METADATA
llm_wrangler-0.4.0.dist-info/WHEEL
llm_wrangler-0.4.0.dist-info/RECORD
